aptamer_generator/__init__.py
aptamer_generator/core.py
aptamer_generator-0.1.1.dist-info/licenses/LICENSE
aptamer_generator-0.1.1.dist-info/METADATA
aptamer_generator-0.1.1.dist-info/WHEEL
aptamer_generator-0.1.1.dist-info/top_level.txt
aptamer_generator-0.1.1.dist-info/RECORD
