Metadata-Version: 2.4
Name: aptamer-generator
Version: 0.1.1
Summary: Aptamer candidate generator with GC content constraints
Author-email: Avinab Neogy <avinabneogy.bits@gmail.com>
License: MIT
Project-URL: repository, https://github.com/avinab-neogy/aptamer-generator
Requires-Python: >=3.8
License-File: LICENSE
Requires-Dist: numpy>=1.21
Requires-Dist: biopython>=1.79
Provides-Extra: test
Requires-Dist: pytest>=7.0; extra == "test"
Requires-Dist: pytest-cov>=3.0; extra == "test"
Dynamic: license-file
